[
  {
    "id": 16818,
    "payslip_status": false,
    "report_note": false,
    "user_id": [
      1328,
      "mbakr.uat"
    ],
    "manager_id": [
      1526,
      "[1688] ايمن بن معتوق السفياني"
    ],
    "notes": "test from api",
    "number_of_days_temp": 0,
    "number_of_days": 0,
    "meeting_id": false,
    "type": "remove",
    "linked_request_ids": [],
    "category_id": false,
    "holiday_type": "employee",
    "first_approver_id": false,
    "second_approver_id": false,
    "name": "15021",
    "date": "2025-02-02",
    "employee_id": [
      1711,
      "[1750] محمود  بن ناصر  البكر"
    ],
    "substitute_employee_id": [
      10,
      "[1010] فايز بن محمد الفايز"
    ],
    "department_id": [
      441,
      "خدمات المنشآت / التقنية والحلول الرقمية / الحلول الرقمية / إدارة الخدمات الرقمية"
    ],
    "job_id": [
      1785,
      "قائد فريق إدارة الخدمات الرقمية"
    ],
    "grade_id": [
      32,
      "قائد فريق"
    ],
    "degree_id": [
      38,
      "12"
    ],
    "raison": "other",
    "date_from": "2030-08-04",
    "date_to": "2030-08-04",
    "duration": 1,
    "holiday_status_id": [
      18,
      "إجازة وفاة"
    ],
    "with_advanced_salary": false,
    "salary_number": 0,
    "state": "hrm",
    "holiday_cancellation": false,
    "is_extension": false,
    "extended_holiday_id": false,
    "parent_id": false,
    "extension_holidays_ids": [],
    "extension_duration": 0,
    "childbirth_date": false,
    "sold_overtime": 0,
    "sold_attendance": 0,
    "death_person": "test",
    "compensation_type": false,
    "accompaniment_type": false,
    "accompanied_child_age": 0,
    "study_subject": false,
    "city": false,
    "country_ids": false,
    "current_holiday_stock": 1,
    "sport_participation_topic": false,
    "birth_child_filename": false,
    "hide_with_advanced_salary": true,
    "token_compensation_stock": 0,
    "payed_salary_advance": false,
    "done_date": "false",
    "attachment_ids": [
      158998
    ],
    "date_holidays_to": false,
    "refuse_reason": "false",
    "active": true,
    "cancel_reason": false,
    "half_day": false,
    "period_type": false,
    "time_from": false,
    "time_to": false,
    "half_day_duration": 0,
    "website_message_ids": [],
    "message_follower_ids": [
      12122581,
      12122582,
      12122589,
      12122590,
      12122591,
      12122592
    ],
    "message_ids": [
      167874042,
      167874035
    ],
    "message_last_post": false,
    "create_uid": [
      1336,
      "asaedi"
    ],
    "create_date": "2025-02-02 12:10:37",
    "write_uid": [
      1336,
      "asaedi"
    ],
    "write_date": "2025-02-02 12:10:37",
    "res_model": "hr.holidays",
    "is_from_mobile": true,
    "mobile_approvals_ids": [],
    "x_sla_labels": "",
    "double_validation": false,
    "can_reset": false,
    "is_annual": false,
    "spend_advanced_salary": false,
    "advanced_salary_period": 30,
    "is_current_user": false,
    "is_direct_manager": false,
    "is_cut": false,
    "is_cancelled": false,
    "is_started": false,
    "is_finished": false,
    "is_extended": false,
    "can_be_cut": true,
    "can_be_cancelled": true,
    "display_button_cancel": false,
    "display_button_cut": false,
    "display_button_extend": false,
    "attachment_required": true,
    "display_button_send": false,
    "substitute_employee_required": false,
    "computed_duration": 1,
    "message_is_follower": false,
    "message_partner_ids": [
      3945,
      1951,
      1037,
      826,
      3667,
      3758
    ],
    "message_channel_ids": [],
    "message_unread": false,
    "message_unread_counter": 0,
    "message_needaction": false,
    "message_needaction_counter": 0,
    "display_name": "محمود  بن ناصر  البكر - إجازة وفاة : 1  يوم",
    "__last_update": "2025-02-02 12:10:37",
    "department_global_id": [
      32,
      "خدمات المنشآت / التقنية والحلول الرقمية"
    ],
    "sector_id": [
      12,
      "خدمات المنشآت"
    ]
  },
  {
    "id": 16757,
    "payslip_status": false,
    "report_note": false,
    "user_id": [
      1328,
      "mbakr.uat"
    ],
    "manager_id": [
      1526,
      "[1688] ايمن بن معتوق السفياني"
    ],
    "notes": "test from api",
    "number_of_days_temp": 0,
    "number_of_days": 0,
    "meeting_id": false,
    "type": "remove",
    "linked_request_ids": [],
    "category_id": false,
    "holiday_type": "employee",
    "first_approver_id": false,
    "second_approver_id": false,
    "name": "14960",
    "date": "2025-01-21",
    "employee_id": [
      1711,
      "[1750] محمود  بن ناصر  البكر"
    ],
    "substitute_employee_id": [
      10,
      "[1010] فايز بن محمد الفايز"
    ],
    "department_id": [
      441,
      "خدمات المنشآت / التقنية والحلول الرقمية / الحلول الرقمية / إدارة الخدمات الرقمية"
    ],
    "job_id": [
      1785,
      "قائد فريق إدارة الخدمات الرقمية"
    ],
    "grade_id": [
      32,
      "قائد فريق"
    ],
    "degree_id": [
      38,
      "12"
    ],
    "raison": "other",
    "date_from": "2028-07-11",
    "date_to": "2028-07-12",
    "duration": 2,
    "holiday_status_id": [
      18,
      "إجازة وفاة"
    ],
    "with_advanced_salary": false,
    "salary_number": 0,
    "state": "done",
    "holiday_cancellation": false,
    "is_extension": false,
    "extended_holiday_id": false,
    "parent_id": false,
    "extension_holidays_ids": [],
    "extension_duration": 0,
    "childbirth_date": false,
    "sold_overtime": 0,
    "sold_attendance": 0,
    "death_person": "test",
    "compensation_type": false,
    "accompaniment_type": false,
    "accompanied_child_age": 0,
    "study_subject": false,
    "city": false,
    "country_ids": false,
    "current_holiday_stock": 3,
    "sport_participation_topic": false,
    "birth_child_filename": false,
    "hide_with_advanced_salary": true,
    "token_compensation_stock": 0,
    "payed_salary_advance": false,
    "done_date": "2025-01-21 09:56:47",
    "attachment_ids": [
      158483
    ],
    "date_holidays_to": false,
    "refuse_reason": "false",
    "active": true,
    "cancel_reason": false,
    "half_day": false,
    "period_type": false,
    "time_from": false,
    "time_to": false,
    "half_day_duration": 0,
    "website_message_ids": [],
    "message_follower_ids": [
      10962982,
      10962984,
      10962985,
      10962986,
      10962987,
      10962988
    ],
    "message_ids": [
      166562813,
      166562796,
      166562793
    ],
    "message_last_post": false,
    "create_uid": [
      1336,
      "asaedi"
    ],
    "create_date": "2025-01-21 09:56:16",
    "write_uid": [
      1336,
      "asaedi"
    ],
    "write_date": "2025-01-21 09:56:46",
    "res_model": "hr.holidays",
    "is_from_mobile": true,
    "mobile_approvals_ids": [],
    "x_sla_labels": "",
    "double_validation": false,
    "can_reset": false,
    "is_annual": false,
    "spend_advanced_salary": false,
    "advanced_salary_period": 30,
    "is_current_user": false,
    "is_direct_manager": false,
    "is_cut": false,
    "is_cancelled": false,
    "is_started": false,
    "is_finished": false,
    "is_extended": false,
    "can_be_cut": true,
    "can_be_cancelled": true,
    "display_button_cancel": false,
    "display_button_cut": false,
    "display_button_extend": false,
    "attachment_required": true,
    "display_button_send": false,
    "substitute_employee_required": false,
    "computed_duration": 2,
    "message_is_follower": false,
    "message_partner_ids": [
      3945,
      1951,
      1037,
      826,
      3667,
      3758
    ],
    "message_channel_ids": [],
    "message_unread": false,
    "message_unread_counter": 0,
    "message_needaction": false,
    "message_needaction_counter": 0,
    "display_name": "محمود  بن ناصر  البكر - إجازة وفاة : 2  يوم",
    "__last_update": "2025-01-21 09:56:46",
    "department_global_id": [
      32,
      "خدمات المنشآت / التقنية والحلول الرقمية"
    ],
    "sector_id": [
      12,
      "خدمات المنشآت"
    ]
  },
  {
    "id": 16756,
    "payslip_status": false,
    "report_note": false,
    "user_id": [
      1328,
      "mbakr.uat"
    ],
    "manager_id": [
      1526,
      "[1688] ايمن بن معتوق السفياني"
    ],
    "notes": "test from api",
    "number_of_days_temp": 0,
    "number_of_days": 0,
    "meeting_id": false,
    "type": "remove",
    "linked_request_ids": [],
    "category_id": false,
    "holiday_type": "employee",
    "first_approver_id": false,
    "second_approver_id": false,
    "name": "14959",
    "date": "2025-01-21",
    "employee_id": [
      1711,
      "[1750] محمود  بن ناصر  البكر"
    ],
    "substitute_employee_id": [
      10,
      "[1010] فايز بن محمد الفايز"
    ],
    "department_id": [
      441,
      "خدمات المنشآت / التقنية والحلول الرقمية / الحلول الرقمية / إدارة الخدمات الرقمية"
    ],
    "job_id": [
      1785,
      "قائد فريق إدارة الخدمات الرقمية"
    ],
    "grade_id": [
      32,
      "قائد فريق"
    ],
    "degree_id": [
      38,
      "12"
    ],
    "raison": "other",
    "date_from": "2029-07-11",
    "date_to": "2029-07-12",
    "duration": 2,
    "holiday_status_id": [
      18,
      "إجازة وفاة"
    ],
    "with_advanced_salary": false,
    "salary_number": 0,
    "state": "done",
    "holiday_cancellation": false,
    "is_extension": false,
    "extended_holiday_id": false,
    "parent_id": false,
    "extension_holidays_ids": [],
    "extension_duration": 0,
    "childbirth_date": false,
    "sold_overtime": 0,
    "sold_attendance": 0,
    "death_person": "test",
    "compensation_type": false,
    "accompaniment_type": false,
    "accompanied_child_age": 0,
    "study_subject": false,
    "city": false,
    "country_ids": false,
    "current_holiday_stock": 5,
    "sport_participation_topic": false,
    "birth_child_filename": false,
    "hide_with_advanced_salary": true,
    "token_compensation_stock": 0,
    "payed_salary_advance": false,
    "done_date": "2025-01-21 09:50:01",
    "attachment_ids": [
      158482
    ],
    "date_holidays_to": false,
    "refuse_reason": "false",
    "active": true,
    "cancel_reason": false,
    "half_day": false,
    "period_type": false,
    "time_from": false,
    "time_to": false,
    "half_day_duration": 0,
    "website_message_ids": [],
    "message_follower_ids": [
      10945067,
      10945068,
      10945069,
      10945071,
      10945072,
      10945073
    ],
    "message_ids": [
      166562727,
      166544878,
      166544870
    ],
    "message_last_post": false,
    "create_uid": [
      1336,
      "asaedi"
    ],
    "create_date": "2025-01-21 09:28:37",
    "write_uid": [
      1336,
      "asaedi"
    ],
    "write_date": "2025-01-21 09:50:00",
    "res_model": "hr.holidays",
    "is_from_mobile": true,
    "mobile_approvals_ids": [],
    "x_sla_labels": "",
    "double_validation": false,
    "can_reset": false,
    "is_annual": false,
    "spend_advanced_salary": false,
    "advanced_salary_period": 30,
    "is_current_user": false,
    "is_direct_manager": false,
    "is_cut": false,
    "is_cancelled": false,
    "is_started": false,
    "is_finished": false,
    "is_extended": false,
    "can_be_cut": true,
    "can_be_cancelled": true,
    "display_button_cancel": false,
    "display_button_cut": false,
    "display_button_extend": false,
    "attachment_required": true,
    "display_button_send": false,
    "substitute_employee_required": false,
    "computed_duration": 2,
    "message_is_follower": false,
    "message_partner_ids": [
      3945,
      1951,
      1037,
      826,
      3667,
      3758
    ],
    "message_channel_ids": [],
    "message_unread": false,
    "message_unread_counter": 0,
    "message_needaction": false,
    "message_needaction_counter": 0,
    "display_name": "محمود  بن ناصر  البكر - إجازة وفاة : 2  يوم",
    "__last_update": "2025-01-21 09:50:00",
    "department_global_id": [
      32,
      "خدمات المنشآت / التقنية والحلول الرقمية"
    ],
    "sector_id": [
      12,
      "خدمات المنشآت"
    ]
  },
  {
    "id": 16197,
    "payslip_status": false,
    "report_note": false,
    "user_id": [
      1328,
      "mbakr.uat"
    ],
    "manager_id": [
      1526,
      "[1688] ايمن بن معتوق السفياني"
    ],
    "notes": "false",
    "number_of_days_temp": 0,
    "number_of_days": 0,
    "meeting_id": false,
    "type": "remove",
    "linked_request_ids": [],
    "category_id": false,
    "holiday_type": "employee",
    "first_approver_id": false,
    "second_approver_id": false,
    "name": "14645",
    "date": "2023-11-19",
    "employee_id": [
      1711,
      "[1750] محمود  بن ناصر  البكر"
    ],
    "substitute_employee_id": [
      517,
      "[1417] رائد بن حمد رشيد"
    ],
    "department_id": [
      441,
      "خدمات المنشآت / التقنية والحلول الرقمية / الحلول الرقمية / إدارة الخدمات الرقمية"
    ],
    "job_id": [
      1785,
      "قائد فريق إدارة الخدمات الرقمية"
    ],
    "grade_id": [
      32,
      "قائد فريق"
    ],
    "degree_id": [
      38,
      "12"
    ],
    "raison": false,
    "date_from": "2023-11-20",
    "date_to": "2023-11-20",
    "duration": 1,
    "holiday_status_id": [
      5,
      "إجازة سنوية #test"
    ],
    "with_advanced_salary": false,
    "salary_number": 0,
    "state": "done",
    "holiday_cancellation": false,
    "is_extension": false,
    "extended_holiday_id": false,
    "parent_id": false,
    "extension_holidays_ids": [],
    "extension_duration": 0,
    "childbirth_date": false,
    "sold_overtime": 0,
    "sold_attendance": 0,
    "death_person": false,
    "compensation_type": false,
    "accompaniment_type": false,
    "accompanied_child_age": 0,
    "study_subject": false,
    "city": false,
    "country_ids": [
      595,
      "Bonaire, Sint Eustatius and Saba"
    ],
    "current_holiday_stock": 15.602739726027403,
    "sport_participation_topic": false,
    "birth_child_filename": false,
    "hide_with_advanced_salary": true,
    "token_compensation_stock": 0,
    "payed_salary_advance": false,
    "done_date": "2023-11-20 05:05:03",
    "attachment_ids": [],
    "date_holidays_to": false,
    "refuse_reason": "false",
    "active": true,
    "cancel_reason": false,
    "half_day": false,
    "period_type": false,
    "time_from": false,
    "time_to": false,
    "half_day_duration": 0,
    "website_message_ids": [],
    "message_follower_ids": [
      259541,
      259542,
      259543,
      259544,
      259545,
      259546
    ],
    "message_ids": [
      154589125,
      154589113,
      154588725,
      154588724
    ],
    "message_last_post": false,
    "create_uid": [
      1328,
      "mbakr.uat"
    ],
    "create_date": "2023-11-19 20:24:05",
    "write_uid": [
      1484,
      "rquwayfil.t.uat"
    ],
    "write_date": "2023-11-20 05:05:03",
    "res_model": "hr.holidays",
    "is_from_mobile": false,
    "mobile_approvals_ids": [],
    "x_sla_labels": "",
    "double_validation": false,
    "can_reset": false,
    "is_annual": true,
    "spend_advanced_salary": false,
    "advanced_salary_period": 30,
    "is_current_user": false,
    "is_direct_manager": false,
    "is_cut": false,
    "is_cancelled": false,
    "is_started": true,
    "is_finished": true,
    "is_extended": false,
    "can_be_cut": false,
    "can_be_cancelled": false,
    "display_button_cancel": false,
    "display_button_cut": false,
    "display_button_extend": false,
    "attachment_required": false,
    "display_button_send": false,
    "substitute_employee_required": false,
    "computed_duration": 1,
    "message_is_follower": false,
    "message_partner_ids": [
      3945,
      1951,
      1037,
      826,
      3667,
      3758
    ],
    "message_channel_ids": [],
    "message_unread": false,
    "message_unread_counter": 0,
    "message_needaction": false,
    "message_needaction_counter": 0,
    "display_name": "محمود  بن ناصر  البكر - إجازة سنوية #test : 1  يوم",
    "__last_update": "2023-11-20 05:05:03",
    "department_global_id": [
      32,
      "خدمات المنشآت / التقنية والحلول الرقمية"
    ],
    "sector_id": [
      12,
      "خدمات المنشآت"
    ]
  },
  {
    "id": 15576,
    "payslip_status": false,
    "report_note": false,
    "user_id": [
      1328,
      "mbakr.uat"
    ],
    "manager_id": [
      1526,
      "[1688] ايمن بن معتوق السفياني"
    ],
    "notes": "false",
    "number_of_days_temp": 0,
    "number_of_days": 0,
    "meeting_id": false,
    "type": "remove",
    "linked_request_ids": [],
    "category_id": false,
    "holiday_type": "employee",
    "first_approver_id": false,
    "second_approver_id": false,
    "name": "14074",
    "date": "2023-09-26",
    "employee_id": [
      1711,
      "[1750] محمود  بن ناصر  البكر"
    ],
    "substitute_employee_id": [
      517,
      "[1417] رائد بن حمد رشيد"
    ],
    "department_id": [
      441,
      "خدمات المنشآت / التقنية والحلول الرقمية / الحلول الرقمية / إدارة الخدمات الرقمية"
    ],
    "job_id": [
      1785,
      "قائد فريق إدارة الخدمات الرقمية"
    ],
    "grade_id": [
      32,
      "قائد فريق"
    ],
    "degree_id": [
      38,
      "12"
    ],
    "raison": false,
    "date_from": "2023-09-28",
    "date_to": "2023-09-28",
    "duration": 1,
    "holiday_status_id": [
      5,
      "إجازة سنوية #test"
    ],
    "with_advanced_salary": false,
    "salary_number": 0,
    "state": "done",
    "holiday_cancellation": false,
    "is_extension": false,
    "extended_holiday_id": false,
    "parent_id": false,
    "extension_holidays_ids": [],
    "extension_duration": 0,
    "childbirth_date": false,
    "sold_overtime": 0,
    "sold_attendance": 0,
    "death_person": false,
    "compensation_type": false,
    "accompaniment_type": false,
    "accompanied_child_age": 0,
    "study_subject": false,
    "city": false,
    "country_ids": [
      595,
      "Bonaire, Sint Eustatius and Saba"
    ],
    "current_holiday_stock": 11.276712328767127,
    "sport_participation_topic": false,
    "birth_child_filename": false,
    "hide_with_advanced_salary": true,
    "token_compensation_stock": 0,
    "payed_salary_advance": false,
    "done_date": "2023-09-27 05:19:12",
    "attachment_ids": [],
    "date_holidays_to": false,
    "refuse_reason": "false",
    "active": true,
    "cancel_reason": false,
    "half_day": false,
    "period_type": false,
    "time_from": false,
    "time_to": false,
    "half_day_duration": 0,
    "website_message_ids": [],
    "message_follower_ids": [
      241674,
      241675,
      241676,
      241677,
      241678,
      241679
    ],
    "message_ids": [
      75940896,
      75868943,
      74718979,
      74718902
    ],
    "message_last_post": false,
    "create_uid": [
      1328,
      "mbakr.uat"
    ],
    "create_date": "2023-09-26 13:14:52",
    "write_uid": [
      1484,
      "rquwayfil.t.uat"
    ],
    "write_date": "2023-09-27 05:19:12",
    "res_model": "hr.holidays",
    "is_from_mobile": false,
    "mobile_approvals_ids": [],
    "x_sla_labels": "",
    "double_validation": false,
    "can_reset": false,
    "is_annual": true,
    "spend_advanced_salary": false,
    "advanced_salary_period": 30,
    "is_current_user": false,
    "is_direct_manager": false,
    "is_cut": false,
    "is_cancelled": false,
    "is_started": true,
    "is_finished": true,
    "is_extended": false,
    "can_be_cut": false,
    "can_be_cancelled": false,
    "display_button_cancel": false,
    "display_button_cut": false,
    "display_button_extend": false,
    "attachment_required": false,
    "display_button_send": false,
    "substitute_employee_required": false,
    "computed_duration": 1,
    "message_is_follower": false,
    "message_partner_ids": [
      3945,
      1951,
      1037,
      826,
      3667,
      3758
    ],
    "message_channel_ids": [],
    "message_unread": false,
    "message_unread_counter": 0,
    "message_needaction": false,
    "message_needaction_counter": 0,
    "display_name": "محمود  بن ناصر  البكر - إجازة سنوية #test : 1  يوم",
    "__last_update": "2023-09-27 05:19:12",
    "department_global_id": [
      32,
      "خدمات المنشآت / التقنية والحلول الرقمية"
    ],
    "sector_id": [
      12,
      "خدمات المنشآت"
    ]
  },
  {
    "id": 14423,
    "payslip_status": false,
    "report_note": false,
    "user_id": [
      1328,
      "mbakr.uat"
    ],
    "manager_id": [
      1526,
      "[1688] ايمن بن معتوق السفياني"
    ],
    "notes": "false",
    "number_of_days_temp": 0,
    "number_of_days": 0,
    "meeting_id": false,
    "type": "remove",
    "linked_request_ids": [],
    "category_id": false,
    "holiday_type": "employee",
    "first_approver_id": false,
    "second_approver_id": false,
    "name": "12960",
    "date": "2023-06-06",
    "employee_id": [
      1711,
      "[1750] محمود  بن ناصر  البكر"
    ],
    "substitute_employee_id": [
      517,
      "[1417] رائد بن حمد رشيد"
    ],
    "department_id": [
      441,
      "خدمات المنشآت / التقنية والحلول الرقمية / الحلول الرقمية / إدارة الخدمات الرقمية"
    ],
    "job_id": [
      1785,
      "قائد فريق إدارة الخدمات الرقمية"
    ],
    "grade_id": [
      32,
      "قائد فريق"
    ],
    "degree_id": [
      38,
      "12"
    ],
    "raison": false,
    "date_from": "2023-07-16",
    "date_to": "2023-07-27",
    "duration": 12,
    "holiday_status_id": [
      5,
      "إجازة سنوية #test"
    ],
    "with_advanced_salary": false,
    "salary_number": 0,
    "state": "done",
    "holiday_cancellation": false,
    "is_extension": false,
    "extended_holiday_id": false,
    "parent_id": false,
    "extension_holidays_ids": [],
    "extension_duration": 0,
    "childbirth_date": false,
    "sold_overtime": 0,
    "sold_attendance": 0,
    "death_person": false,
    "compensation_type": false,
    "accompaniment_type": false,
    "accompanied_child_age": 0,
    "study_subject": false,
    "city": false,
    "country_ids": [
      595,
      "Bonaire, Sint Eustatius and Saba"
    ],
    "current_holiday_stock": 12.131506849315072,
    "sport_participation_topic": false,
    "birth_child_filename": false,
    "hide_with_advanced_salary": true,
    "token_compensation_stock": 0,
    "payed_salary_advance": false,
    "done_date": "2023-06-07 08:39:43",
    "attachment_ids": [],
    "date_holidays_to": false,
    "refuse_reason": "false",
    "active": true,
    "cancel_reason": false,
    "half_day": false,
    "period_type": false,
    "time_from": false,
    "time_to": false,
    "half_day_duration": 0,
    "website_message_ids": [],
    "message_follower_ids": [
      220311,
      220312,
      220313,
      220314,
      220315,
      220316
    ],
    "message_ids": [
      21181822,
      21181789,
      21178778,
      21178777
    ],
    "message_last_post": false,
    "create_uid": [
      1328,
      "mbakr.uat"
    ],
    "create_date": "2023-06-06 07:33:18",
    "write_uid": [
      653,
      "nnabulsi.uat"
    ],
    "write_date": "2023-06-07 08:39:43",
    "res_model": "hr.holidays",
    "is_from_mobile": false,
    "mobile_approvals_ids": [],
    "x_sla_labels": "",
    "double_validation": false,
    "can_reset": false,
    "is_annual": true,
    "spend_advanced_salary": false,
    "advanced_salary_period": 30,
    "is_current_user": false,
    "is_direct_manager": false,
    "is_cut": false,
    "is_cancelled": false,
    "is_started": true,
    "is_finished": true,
    "is_extended": false,
    "can_be_cut": false,
    "can_be_cancelled": false,
    "display_button_cancel": false,
    "display_button_cut": false,
    "display_button_extend": false,
    "attachment_required": false,
    "display_button_send": false,
    "substitute_employee_required": false,
    "computed_duration": 12,
    "message_is_follower": false,
    "message_partner_ids": [
      3945,
      1951,
      1037,
      826,
      3667,
      3758
    ],
    "message_channel_ids": [],
    "message_unread": false,
    "message_unread_counter": 0,
    "message_needaction": false,
    "message_needaction_counter": 0,
    "display_name": "محمود  بن ناصر  البكر - إجازة سنوية #test : 12  يوم",
    "__last_update": "2023-06-07 08:39:43",
    "department_global_id": [
      32,
      "خدمات المنشآت / التقنية والحلول الرقمية"
    ],
    "sector_id": [
      12,
      "خدمات المنشآت"
    ]
  },
  {
    "id": 13947,
    "payslip_status": false,
    "report_note": false,
    "user_id": [
      1328,
      "mbakr.uat"
    ],
    "manager_id": [
      1526,
      "[1688] ايمن بن معتوق السفياني"
    ],
    "notes": "false",
    "number_of_days_temp": 0,
    "number_of_days": 0,
    "meeting_id": false,
    "type": "remove",
    "linked_request_ids": [],
    "category_id": false,
    "holiday_type": "employee",
    "first_approver_id": false,
    "second_approver_id": false,
    "name": "12511",
    "date": "2023-04-13",
    "employee_id": [
      1711,
      "[1750] محمود  بن ناصر  البكر"
    ],
    "substitute_employee_id": [
      517,
      "[1417] رائد بن حمد رشيد"
    ],
    "department_id": [
      441,
      "خدمات المنشآت / التقنية والحلول الرقمية / الحلول الرقمية / إدارة الخدمات الرقمية"
    ],
    "job_id": [
      1785,
      "قائد فريق إدارة الخدمات الرقمية"
    ],
    "grade_id": [
      32,
      "قائد فريق"
    ],
    "degree_id": [
      38,
      "12"
    ],
    "raison": false,
    "date_from": "2023-07-09",
    "date_to": "2023-07-13",
    "duration": 5,
    "holiday_status_id": [
      25,
      "إجازة زواج"
    ],
    "with_advanced_salary": false,
    "salary_number": 0,
    "state": "done",
    "holiday_cancellation": false,
    "is_extension": false,
    "extended_holiday_id": false,
    "parent_id": false,
    "extension_holidays_ids": [],
    "extension_duration": 0,
    "childbirth_date": false,
    "sold_overtime": 0,
    "sold_attendance": 0,
    "death_person": false,
    "compensation_type": false,
    "accompaniment_type": false,
    "accompanied_child_age": 0,
    "study_subject": false,
    "city": false,
    "country_ids": [
      595,
      "Bonaire, Sint Eustatius and Saba"
    ],
    "current_holiday_stock": 5,
    "sport_participation_topic": false,
    "birth_child_filename": false,
    "hide_with_advanced_salary": true,
    "token_compensation_stock": 0,
    "payed_salary_advance": false,
    "done_date": "2023-04-13 10:08:15",
    "attachment_ids": [],
    "date_holidays_to": false,
    "refuse_reason": "false",
    "active": true,
    "cancel_reason": false,
    "half_day": false,
    "period_type": false,
    "time_from": false,
    "time_to": false,
    "half_day_duration": 0,
    "website_message_ids": [],
    "message_follower_ids": [
      209497,
      209498,
      209499,
      209500,
      209501,
      209502
    ],
    "message_ids": [
      20929139,
      20929127,
      20927052,
      20927048
    ],
    "message_last_post": false,
    "create_uid": [
      1328,
      "mbakr.uat"
    ],
    "create_date": "2023-04-13 07:51:44",
    "write_uid": [
      653,
      "nnabulsi.uat"
    ],
    "write_date": "2023-04-13 10:08:15",
    "res_model": "hr.holidays",
    "is_from_mobile": false,
    "mobile_approvals_ids": [
      6090
    ],
    "x_sla_labels": "",
    "double_validation": false,
    "can_reset": false,
    "is_annual": false,
    "spend_advanced_salary": false,
    "advanced_salary_period": 30,
    "is_current_user": false,
    "is_direct_manager": false,
    "is_cut": false,
    "is_cancelled": false,
    "is_started": true,
    "is_finished": true,
    "is_extended": false,
    "can_be_cut": true,
    "can_be_cancelled": true,
    "display_button_cancel": false,
    "display_button_cut": false,
    "display_button_extend": false,
    "attachment_required": false,
    "display_button_send": false,
    "substitute_employee_required": false,
    "computed_duration": 5,
    "message_is_follower": false,
    "message_partner_ids": [
      3945,
      1951,
      1037,
      826,
      3667,
      3758
    ],
    "message_channel_ids": [],
    "message_unread": false,
    "message_unread_counter": 0,
    "message_needaction": false,
    "message_needaction_counter": 0,
    "display_name": "محمود  بن ناصر  البكر - إجازة زواج : 5  يوم",
    "__last_update": "2023-04-13 10:08:15",
    "department_global_id": [
      32,
      "خدمات المنشآت / التقنية والحلول الرقمية"
    ],
    "sector_id": [
      12,
      "خدمات المنشآت"
    ]
  }
]